MANIFEST.in
README.rst
setup.cfg
setup.py
src/gitlab_auto_close_issue/__init__.py
src/gitlab_auto_close_issue/cli.py
src/gitlab_auto_close_issue.egg-info/PKG-INFO
src/gitlab_auto_close_issue.egg-info/SOURCES.txt
src/gitlab_auto_close_issue.egg-info/dependency_links.txt
src/gitlab_auto_close_issue.egg-info/entry_points.txt
src/gitlab_auto_close_issue.egg-info/not-zip-safe
src/gitlab_auto_close_issue.egg-info/requires.txt
src/gitlab_auto_close_issue.egg-info/top_level.txt