Metadata-Version: 2.1
Name: gitlab-auto-close-issue
Version: 0.1.0
Summary: Python script which will automatically close issues on GitLab for you.
Home-page: https://gitlab.com/gitlab-automation-toolkit/gitlab-auto-close-issue
Author: Haseeb Majid
Author-email: me@haseebmajid.dev
License: Apache License
Platform: UNKNOWN
Classifier: Programming Language :: Python
Classifier: Intended Audience :: Developers
Classifier: Operating System :: OS Independent
Classifier: Topic :: Software Development :: Libraries :: Python Modules
Requires-Python: ~=3.7
